mailcap_fix/__init__.py
mailcap_fix/mailcap_fix.py
mailcap_fix/mailcap_original.py
mailcap_fix-1.0.1.dist-info/WHEEL
mailcap_fix-1.0.1.dist-info/METADATA
mailcap_fix-1.0.1.dist-info/DESCRIPTION.rst
mailcap_fix-1.0.1.dist-info/metadata.json
mailcap_fix-1.0.1.dist-info/top_level.txt
mailcap_fix-1.0.1.dist-info/RECORD
