Metadata-Version: 2.0
Name: mailcap-fix
Version: 1.0.1
Summary: A patched mailcap module that conforms to RFC 1524
Home-page: https://github.com/michael-lazar/mailcap_fix
Author: Michael Lazar
Author-email: lazar.michael22@gmail.com
License: UNLICENSE
Keywords: mailcap 1524
Platform: UNKNOWN
